Workbook

Sheet Sheet1

Sheet Sales_Practice
A1: Employee | B1: Department | C1: Product | D1: Quantity | E1: Unit Price | F1: Discount % | H1: Total Amount (Practice) | I1: Discount Amount (Practice) | J1: Final Amount (Practice) | K1: Type (Practice)
A2: Asha | B2: Sales | C2: Laptop | D2: 2 | E2: 55000 | F2: 5
A3: Ravi | B3: Sales | C3: Mouse | D3: 10 | E3: 800 | F3: 10
A4: John | B4: HR | C4: Keyboard | D4: 5 | E4: 1225.567 | F4: 0
A5: Priya | B5: Finance | C5: Monitor | D5: 3 | E5: 15000 | F5: 8
A6: Kiran | B6: Sales | C6: Laptop | D6: 1 | E6: 62000 | F6: 12
A7: Neha | B7: HR | C7: Mouse | D7: 8 | E7: 750 | F7: 5
A8: Arjun | B8: Finance | C8: Monitor | D8: 4 | E8: 14000 | F8: 10
A9: Sana | B9: Sales | C9: Keyboard | D9: 6 | E9: 1100 | F9: 7
D10: =SUM(D2:D9) -> 39 | E10: =SUM(E2:E9) -> 149875.57

Sheet Student_Practice
A1: Student | B1: Python | C1: SQL | D1: Excel | E1: Power BI | F1: Total (Practice) | G1: Average (Practice) | H1: Result (Practice)
A2: Rahul | B2: 78 | C2: 82 | D2: 88 | E2: 75 | H2: =SUM(B2:E2) -> 323
A3: Sita | B3: 85 | C3: 79 | D3: 91 | E3: 87
A4: Arun | B4: 67 | C4: 72 | D4: 70 | E4: 65
A5: Meena | B5: 92 | C5: 90 | D5: 95 | E5: 93
A6: Vijay | B6: 74 | C6: 68 | D6: 76 | E6: 71
A7: Amina | B7: 88 | C7: 84 | D7: 89 | E7: 86
A8: Karthik | B8: 61 | C8: 65 | D8: 69 | E8: 63
A9: Divya | B9: 95 | C9: 91 | D9: 94 | E9: 96

Sheet Instructions
A1: Topic | B1: Syntax | C1: Practice
A2: SUM | B2: =SUM(range) -> #NAME? | C2: Find total Quantity | E2: =SUM(Sales_Practice!D2:D9) -> 39
A3: AVERAGE | B3: =AVERAGE(range) -> #NAME? | C3: Find average Unit Price | E3: =AVERAGE(Sales_Practice!E2:E9) -> 18734.446
A4: MIN | B4: =MIN(range) -> #NAME? | C4: Find lowest Unit Price | E4: =MIN(Sales_Practice!E2:E9) -> 750
A5: MAX | B5: =MAX(range) -> #NAME? | C5: Find highest Unit Price | E5: =MAX(Sales_Practice!E2:E9) -> 62000
A6: COUNT | B6: =COUNT(range) -> 0 | C6: Count numeric Quantity values | E6: =COUNT(Sales_Practice!D2:D9) -> 8
A7: COUNTA | B7: =COUNTA(range) -> 1 | C7: Count employee names | E7: =COUNTA(Sales_Practice!A2:A9) -> 8
A8: IF | B8: =IF(condition,value_if_true,value_if_false) -> #NAME? | C8: If Quantity >= 5, write Bulk else Normal | G8: {=IF(Sales_Practice!D2:D9>=5,"BULK","NORMAL")} -> NORMAL
A9: COUNTIF | B9: =COUNTIF(range,_xlnm.criteria) -> #NAME? | C9: Count Sales department employees | E9: =COUNTIF(Sales_Practice!B1:B9,Sales_Practice!B3) -> 4 | G9: BULK
A10: SUMIF | B10: =SUMIF(range,_xlnm.criteria,sum_range) -> #NAME? | C10: Find total Quantity for Sales | E10: =SUMIF(Sales_Practice!B1:B9,Sales_Practice!B2,Sales_Practice!D2:D9) -> 62 | G10: BULK
A11: ROUND | B11: =ROUND(number,num_digits) -> #NAME? | C11: Round a calculated value | G11: NORMAL
A12: Percentage | B12: =value*percentage -> #NAME? | C12: Calculate 10% of Unit Price | E12: =SUM(Sales_Practice!E2*10%) -> 5500 | G12: NORMAL
A13: Discount | B13: =amount*discount% -> #NAME? | C13: Calculate discount amount | D13: =SUM(Sales_Practice!E10/100) -> 1498.7557 | E13: =SUM(Sales_Practice!E3*10%) -> 80 | G13: BULK
E14: =SUM(Sales_Practice!E4*10%) -> 122.5567 | G14: NORMAL
E15: =SUM(Sales_Practice!E5*10%) -> 1500 | G15: BULK
E16: =SUM(Sales_Practice!E6*10%) -> 6200
E17: =SUM(Sales_Practice!E7*10%) -> 75

Sheet Expenses_Practice
A1: Category | B1: Amount
A2: Food | B2: 4500
A3: Travel | B3: 1800
A4: Rent | B4: 12000
A5: Internet | B5: 900
A6: Food | B6: 5200
A7: Travel | B7: 2200
A8: Electricity | B8: 1500
A9: Internet | B9: 900

Sheet Formula_Practice
A1: Question | B1: Formula_To_Write | C1: Your_Answer
A2: 1. Find total quantity | B2: SUM
A3: 2. Find average unit price | B3: AVERAGE
A4: 3. Find minimum unit price | B4: MINIMUM
A5: 4. Find maximum unit price | B5: MAXIMUM
A6: 5. Count quantity entries | B6: COUNT
A7: 6. Count employee names | B7: COUNT
A8: 7. Count Sales employees using COUNTIF | B8: COUNTIF
A9: 8. Find Sales quantity using SUMIF | B9: SUMIF
A10: 9. Calculate discount amount for first row | B10: SUM AMOUNT /100
A11: 10. Calculate final amount for first row | B11: SUM
A12: 11. Find average Python marks | B12: AVERAGE
A13: 12. Find highest Excel mark | B13: HIGHEST
... A16: 15. Find total Food expenses using SUMIF | B16: SUM
